conflumb/__init__.py
conflumb/confluence_api.py
conflumb/confluence_wrapper.py
conflumb/utils/__init__.py
conflumb/utils/exception.py
conflumb/utils/io_helper.py
conflumb/utils/singleton.py
conflumb-0.1.2.dist-info/LICENSE
conflumb-0.1.2.dist-info/METADATA
conflumb-0.1.2.dist-info/WHEEL
conflumb-0.1.2.dist-info/top_level.txt
conflumb-0.1.2.dist-info/RECORD
